LICENSE
MANIFEST.in
README.rst
setup.py
graphene_ai/__init__.py
graphene_ai/graphene.py
graphene_ai.egg-info/PKG-INFO
graphene_ai.egg-info/SOURCES.txt
graphene_ai.egg-info/dependency_links.txt
graphene_ai.egg-info/entry_points.txt
graphene_ai.egg-info/requires.txt
graphene_ai.egg-info/top_level.txt