Metadata-Version: 1.0
Name: graphene-ai
Version: 0.1
Summary: Graphene AI API.
Home-page: https://github.com/graphene-ai/python-graphene-ai
Author: Francis Bautista
Author-email: francis.bautista07@gmail.com
License: UNKNOWN
Keywords: GRAPHENE,AI,NATURAL LANGUAGE PROCESSING,MULTILINGUAL
Platform: UNKNOWN
